pyctyun/.DS_Store
pyctyun/__init__.py
pyctyun/apis/__init__.py
pyctyun/apis/base.py
pyctyun/apis/compute/__init__.py
pyctyun/apis/iam/__init__.py
pyctyun/apis/iam/delegate.py
pyctyun/apis/iam/iam.py
pyctyun/apis/monitor/__init__.py
pyctyun/apis/monitor/monitor.py
pyctyun/apis/monitor/monitor_item.py
pyctyun/apis/network/__init__.py
pyctyun/apis/network/acl.py
pyctyun/apis/network/dhcp.py
pyctyun/apis/network/eip.py
pyctyun/apis/network/elb.py
pyctyun/apis/network/havip.py
pyctyun/apis/network/health_check.py
pyctyun/apis/network/listener.py
pyctyun/apis/network/nat.py
pyctyun/apis/network/policy.py
pyctyun/apis/network/prefix_list.py
pyctyun/apis/network/security_group.py
pyctyun/apis/network/subnet.py
pyctyun/apis/network/vpc.py
pyctyun/apis/network/zone.py
pyctyun/apis/network/zone_record.py
pyctyun/apis/sdwan/__init__.py
pyctyun/apis/storage/__init__.py
pyctyun/auth.py
pyctyun/exceptions.py
pyctyun/param/__init__.py
pyctyun/param/acl.py
pyctyun/param/dhcp.py
pyctyun/param/eip.py
pyctyun/param/endpoint.py
pyctyun/param/endpoint_service.py
pyctyun/param/endpoint_service_rule.py
pyctyun/param/endpoint_service_transit_ip.py
pyctyun/param/endpoint_service_whitelist.py
pyctyun/param/havip.py
pyctyun/param/health_check.py
pyctyun/param/monitor.py
pyctyun/param/montior_item.py
pyctyun/param/nat.py
pyctyun/param/prefix_list.py
pyctyun/param/security_group.py
pyctyun/param/subnet.py
pyctyun/param/vpc.py
pyctyun/param/zone.py
pyctyun/param/zone_record.py
pyctyun/response/__init__.py
pyctyun/response/base.py
pyctyun/response/dhcp.py
pyctyun/response/eip.py
pyctyun/response/havip.py
pyctyun/response/monitor.py
pyctyun/response/monitor_item.py
pyctyun/response/prefix_list.py
pyctyun/response/security_group.py
pyctyun/response/subnet.py
pyctyun/response/vpc.py
pyctyun/response/zone.py
pyctyun/response/zone_record.py
pyctyun/rules/__init__.py
pyctyun/rules/rule.py
pyctyun/transport.py
pyctyun-0.1.3.dist-info/WHEEL
pyctyun-0.1.3.dist-info/METADATA
pyctyun-0.1.3.dist-info/licenses/LICENSE
pyctyun-0.1.3.dist-info/RECORD
