Metadata-Version: 2.1
Name: pyctyun
Version: 0.1.3
Summary: ctapi python sdk
License: MIT
Author-email: fatelei <fatelei@gmail.com>
Requires-Python: >=3.11
Requires-Dist: email-validator>=2.1.1
Requires-Dist: ipython>=8.27.0
Requires-Dist: pydantic-core>=2.33.0
Requires-Dist: pydantic>=2.11.1
Requires-Dist: pytest-cov>=5.0.0
Requires-Dist: requests>=2.32.3
Requires-Dist: ruff>=0.4.8
